<annotation>
	<folder>training</folder>
	<filename>1085.jpg</filename>
	<path>/home/sdac_seminar/sdac_seminar_sose22/dataset/training/images/1085.jpg</path>
	<source>
		<database>Source</database>
	</source>
	<segmented>0</segmented>
	<size>
		<width>1024</width>
		<height>1024</height>
		<depth>3</depth>
	</size>
	<object>
		<name>Wechselschalter</name>
		<pose>Front</pose>
		<truncated>0</truncated>
		<bndbox>
			<xmin>480</xmin>
			<ymin>649</ymin>
			<xmax>582</xmax>
			<ymax>753</ymax>
		</bndbox>
	</object>
	<object>
		<name>Schukosteckdose_einfach</name>
		<pose>Front</pose>
		<truncated>0</truncated>
		<bndbox>
			<xmin>514</xmin>
			<ymin>170</ymin>
			<xmax>580</xmax>
			<ymax>237</ymax>
		</bndbox>
	</object>
	<object>
		<name>NAM-Nichtautomatischer_Melder</name>
		<pose>Front</pose>
		<truncated>0</truncated>
		<bndbox>
			<xmin>756</xmin>
			<ymin>553</ymin>
			<xmax>822</xmax>
			<ymax>619</ymax>
		</bndbox>
	</object>
	<object>
		<name>Taster_beleuchtet</name>
		<pose>Front</pose>
		<truncated>0</truncated>
		<bndbox>
			<xmin>531</xmin>
			<ymin>411</ymin>
			<xmax>564</xmax>
			<ymax>444</ymax>
		</bndbox>
	</object>
</annotation>