<annotation>
	<folder>training</folder>
	<filename>1889.jpg</filename>
	<path>/home/sdac_seminar/sdac_seminar_sose22/dataset/training/images/1889.jpg</path>
	<source>
		<database>Source</database>
	</source>
	<segmented>0</segmented>
	<size>
		<width>1024</width>
		<height>1024</height>
		<depth>3</depth>
	</size>
	<object>
		<name>OKW_Multisensormelder_(Kombination_optischer_Rauch-Kahlenmonoxid_Waerme-Melder)</name>
		<pose>Front</pose>
		<truncated>0</truncated>
		<bndbox>
			<xmin>698</xmin>
			<ymin>685</ymin>
			<xmax>830</xmax>
			<ymax>817</ymax>
		</bndbox>
	</object>
	<object>
		<name>Ambulanz_Pendelleuchte_LED</name>
		<pose>Front</pose>
		<truncated>0</truncated>
		<bndbox>
			<xmin>153</xmin>
			<ymin>274</ymin>
			<xmax>935</xmax>
			<ymax>454</ymax>
		</bndbox>
	</object>
	<object>
		<name>OKW_Multisensormelder_(Kombination_optischer_Rauch-Kahlenmonoxid_Waerme-Melder)</name>
		<pose>Front</pose>
		<truncated>0</truncated>
		<bndbox>
			<xmin>370</xmin>
			<ymin>646</ymin>
			<xmax>502</xmax>
			<ymax>778</ymax>
		</bndbox>
	</object>
</annotation>