<annotation>
	<folder>training</folder>
	<filename>1892.jpg</filename>
	<path>/home/sdac_seminar/sdac_seminar_sose22/dataset/training/images/1892.jpg</path>
	<source>
		<database>Source</database>
	</source>
	<segmented>0</segmented>
	<size>
		<width>1024</width>
		<height>1024</height>
		<depth>3</depth>
	</size>
	<object>
		<name>OT_Multisensormelder_(Kombination_RMO_WMD)</name>
		<pose>Front</pose>
		<truncated>0</truncated>
		<bndbox>
			<xmin>624</xmin>
			<ymin>688</ymin>
			<xmax>737</xmax>
			<ymax>801</ymax>
		</bndbox>
	</object>
	<object>
		<name>Datenanschluss_einfach</name>
		<pose>Front</pose>
		<truncated>0</truncated>
		<bndbox>
			<xmin>489</xmin>
			<ymin>790</ymin>
			<xmax>539</xmax>
			<ymax>824</ymax>
		</bndbox>
	</object>
	<object>
		<name>OT_Multisensormelder_(Kombination_RMO_WMD)</name>
		<pose>Front</pose>
		<truncated>0</truncated>
		<bndbox>
			<xmin>343</xmin>
			<ymin>171</ymin>
			<xmax>504</xmax>
			<ymax>332</ymax>
		</bndbox>
	</object>
	<object>
		<name>Datenanschluss_einfach</name>
		<pose>Front</pose>
		<truncated>0</truncated>
		<bndbox>
			<xmin>867</xmin>
			<ymin>130</ymin>
			<xmax>967</xmax>
			<ymax>199</ymax>
		</bndbox>
	</object>
</annotation>