<annotation>
	<folder>training</folder>
	<filename>196.jpg</filename>
	<path>/home/sdac_seminar/sdac_seminar_sose22/dataset/training/images/196.jpg</path>
	<source>
		<database>Source</database>
	</source>
	<segmented>0</segmented>
	<size>
		<width>1024</width>
		<height>1024</height>
		<depth>3</depth>
	</size>
	<object>
		<name>KFO_Kamera_mit_Festobjektiv</name>
		<pose>Front</pose>
		<truncated>0</truncated>
		<bndbox>
			<xmin>839</xmin>
			<ymin>252</ymin>
			<xmax>956</xmax>
			<ymax>371</ymax>
		</bndbox>
	</object>
	<object>
		<name>OT_Multisensormelder_(Kombination_RMO_WMD)</name>
		<pose>Front</pose>
		<truncated>0</truncated>
		<bndbox>
			<xmin>470</xmin>
			<ymin>752</ymin>
			<xmax>583</xmax>
			<ymax>865</ymax>
		</bndbox>
	</object>
	<object>
		<name>KFO_Kamera_mit_Festobjektiv</name>
		<pose>Front</pose>
		<truncated>0</truncated>
		<bndbox>
			<xmin>155</xmin>
			<ymin>180</ymin>
			<xmax>246</xmax>
			<ymax>257</ymax>
		</bndbox>
	</object>
</annotation>