<annotation>
	<folder>training</folder>
	<filename>2451.jpg</filename>
	<path>/home/sdac_seminar/sdac_seminar_sose22/dataset/training/images/2451.jpg</path>
	<source>
		<database>Source</database>
	</source>
	<segmented>0</segmented>
	<size>
		<width>1024</width>
		<height>1024</height>
		<depth>3</depth>
	</size>
	<object>
		<name>Schukosteckdose_einfach</name>
		<pose>Front</pose>
		<truncated>0</truncated>
		<bndbox>
			<xmin>278</xmin>
			<ymin>275</ymin>
			<xmax>321</xmax>
			<ymax>325</ymax>
		</bndbox>
	</object>
	<object>
		<name>Datenanschluss_zweifach</name>
		<pose>Front</pose>
		<truncated>0</truncated>
		<bndbox>
			<xmin>419</xmin>
			<ymin>489</ymin>
			<xmax>530</xmax>
			<ymax>614</ymax>
		</bndbox>
	</object>
	<object>
		<name>Scheinwerfer_fuer_Alarmbeleuchtung</name>
		<pose>Front</pose>
		<truncated>0</truncated>
		<bndbox>
			<xmin>435</xmin>
			<ymin>603</ymin>
			<xmax>699</xmax>
			<ymax>828</ymax>
		</bndbox>
	</object>
	<object>
		<name>Schukosteckdose_einfach</name>
		<pose>Front</pose>
		<truncated>0</truncated>
		<bndbox>
			<xmin>303</xmin>
			<ymin>477</ymin>
			<xmax>415</xmax>
			<ymax>578</ymax>
		</bndbox>
	</object>
	<object>
		<name>Scheinwerfer_fuer_Alarmbeleuchtung</name>
		<pose>Front</pose>
		<truncated>0</truncated>
		<bndbox>
			<xmin>830</xmin>
			<ymin>168</ymin>
			<xmax>1024</xmax>
			<ymax>459</ymax>
		</bndbox>
	</object>
</annotation>