<annotation>
	<folder>training</folder>
	<filename>2842.jpg</filename>
	<path>/home/sdac_seminar/sdac_seminar_sose22/dataset/training/images/2842.jpg</path>
	<source>
		<database>Source</database>
	</source>
	<segmented>0</segmented>
	<size>
		<width>1024</width>
		<height>1024</height>
		<depth>3</depth>
	</size>
	<object>
		<name>Gegensprechanlage_mit_Video</name>
		<pose>Front</pose>
		<truncated>0</truncated>
		<bndbox>
			<xmin>330</xmin>
			<ymin>671</ymin>
			<xmax>525</xmax>
			<ymax>861</ymax>
		</bndbox>
	</object>
	<object>
		<name>Ausschalter_beleuchtet</name>
		<pose>Front</pose>
		<truncated>0</truncated>
		<bndbox>
			<xmin>271</xmin>
			<ymin>375</ymin>
			<xmax>327</xmax>
			<ymax>423</ymax>
		</bndbox>
	</object>
	<object>
		<name>Downlight_LED_Einbauleuchten_Flur</name>
		<pose>Front</pose>
		<truncated>0</truncated>
		<bndbox>
			<xmin>756</xmin>
			<ymin>340</ymin>
			<xmax>907</xmax>
			<ymax>468</ymax>
		</bndbox>
	</object>
	<object>
		<name>Einbaudownlights_LED_Konferenzraeume</name>
		<pose>Front</pose>
		<truncated>0</truncated>
		<bndbox>
			<xmin>509</xmin>
			<ymin>484</ymin>
			<xmax>659</xmax>
			<ymax>588</ymax>
		</bndbox>
	</object>
	<object>
		<name>Downlight_LED_Einbauleuchten_Flur</name>
		<pose>Front</pose>
		<truncated>0</truncated>
		<bndbox>
			<xmin>771</xmin>
			<ymin>184</ymin>
			<xmax>864</xmax>
			<ymax>312</ymax>
		</bndbox>
	</object>
</annotation>