<annotation>
	<folder>training</folder>
	<filename>2954.jpg</filename>
	<path>/home/sdac_seminar/sdac_seminar_sose22/dataset/training/images/2954.jpg</path>
	<source>
		<database>Source</database>
	</source>
	<segmented>0</segmented>
	<size>
		<width>1024</width>
		<height>1024</height>
		<depth>3</depth>
	</size>
	<object>
		<name>Datenanschluss_zweifach</name>
		<pose>Front</pose>
		<truncated>0</truncated>
		<bndbox>
			<xmin>866</xmin>
			<ymin>806</ymin>
			<xmax>917</xmax>
			<ymax>840</ymax>
		</bndbox>
	</object>
	<object>
		<name>OKW_Multisensormelder_(Kombination_optischer_Rauch-Kahlenmonoxid_Waerme-Melder)</name>
		<pose>Front</pose>
		<truncated>0</truncated>
		<bndbox>
			<xmin>75</xmin>
			<ymin>765</ymin>
			<xmax>141</xmax>
			<ymax>831</ymax>
		</bndbox>
	</object>
	<object>
		<name>Zimmersignalleuchte</name>
		<pose>Front</pose>
		<truncated>0</truncated>
		<bndbox>
			<xmin>361</xmin>
			<ymin>451</ymin>
			<xmax>641</xmax>
			<ymax>733</ymax>
		</bndbox>
	</object>
</annotation>