<annotation>
	<folder>training</folder>
	<filename>312.jpg</filename>
	<path>/home/sdac_seminar/sdac_seminar_sose22/dataset/training/images/312.jpg</path>
	<source>
		<database>Source</database>
	</source>
	<segmented>0</segmented>
	<size>
		<width>1024</width>
		<height>1024</height>
		<depth>3</depth>
	</size>
	<object>
		<name>Taster_beleuchtet</name>
		<pose>Front</pose>
		<truncated>0</truncated>
		<bndbox>
			<xmin>718</xmin>
			<ymin>769</ymin>
			<xmax>784</xmax>
			<ymax>835</ymax>
		</bndbox>
	</object>
	<object>
		<name>WLAN</name>
		<pose>Front</pose>
		<truncated>0</truncated>
		<bndbox>
			<xmin>853</xmin>
			<ymin>477</ymin>
			<xmax>957</xmax>
			<ymax>582</ymax>
		</bndbox>
	</object>
	<object>
		<name>Serienschalter</name>
		<pose>Front</pose>
		<truncated>0</truncated>
		<bndbox>
			<xmin>369</xmin>
			<ymin>843</ymin>
			<xmax>465</xmax>
			<ymax>919</ymax>
		</bndbox>
	</object>
	<object>
		<name>Downlight_LED_Einbauleuchten_Flur</name>
		<pose>Front</pose>
		<truncated>0</truncated>
		<bndbox>
			<xmin>167</xmin>
			<ymin>181</ymin>
			<xmax>231</xmax>
			<ymax>227</ymax>
		</bndbox>
	</object>
	<object>
		<name>Taster_beleuchtet</name>
		<pose>Front</pose>
		<truncated>0</truncated>
		<bndbox>
			<xmin>451</xmin>
			<ymin>551</ymin>
			<xmax>517</xmax>
			<ymax>617</ymax>
		</bndbox>
	</object>
	<object>
		<name>WLAN</name>
		<pose>Front</pose>
		<truncated>0</truncated>
		<bndbox>
			<xmin>54</xmin>
			<ymin>240</ymin>
			<xmax>164</xmax>
			<ymax>349</ymax>
		</bndbox>
	</object>
	<object>
		<name>Serienschalter</name>
		<pose>Front</pose>
		<truncated>0</truncated>
		<bndbox>
			<xmin>563</xmin>
			<ymin>492</ymin>
			<xmax>611</xmax>
			<ymax>576</ymax>
		</bndbox>
	</object>
	<object>
		<name>Serienschalter</name>
		<pose>Front</pose>
		<truncated>0</truncated>
		<bndbox>
			<xmin>859</xmin>
			<ymin>480</ymin>
			<xmax>955</xmax>
			<ymax>648</ymax>
		</bndbox>
	</object>
</annotation>