<annotation>
	<folder>training</folder>
	<filename>3180.jpg</filename>
	<path>/home/sdac_seminar/sdac_seminar_sose22/dataset/training/images/3180.jpg</path>
	<source>
		<database>Source</database>
	</source>
	<segmented>0</segmented>
	<size>
		<width>1024</width>
		<height>1024</height>
		<depth>3</depth>
	</size>
	<object>
		<name>Gegensprechanlage_mit_Video</name>
		<pose>Front</pose>
		<truncated>0</truncated>
		<bndbox>
			<xmin>784</xmin>
			<ymin>155</ymin>
			<xmax>960</xmax>
			<ymax>250</ymax>
		</bndbox>
	</object>
	<object>
		<name>ASR_Ansaugrauchmelder</name>
		<pose>Front</pose>
		<truncated>0</truncated>
		<bndbox>
			<xmin>334</xmin>
			<ymin>573</ymin>
			<xmax>459</xmax>
			<ymax>698</ymax>
		</bndbox>
	</object>
	<object>
		<name>Einbaudownlights_LED_Konferenzraeume</name>
		<pose>Front</pose>
		<truncated>0</truncated>
		<bndbox>
			<xmin>615</xmin>
			<ymin>736</ymin>
			<xmax>765</xmax>
			<ymax>840</ymax>
		</bndbox>
	</object>
	<object>
		<name>Downlight_LED_Einbauleuchten_Flur</name>
		<pose>Front</pose>
		<truncated>0</truncated>
		<bndbox>
			<xmin>133</xmin>
			<ymin>844</ymin>
			<xmax>226</xmax>
			<ymax>972</ymax>
		</bndbox>
	</object>
	<object>
		<name>ASR_Ansaugrauchmelder</name>
		<pose>Front</pose>
		<truncated>0</truncated>
		<bndbox>
			<xmin>265</xmin>
			<ymin>710</ymin>
			<xmax>327</xmax>
			<ymax>772</ymax>
		</bndbox>
	</object>
</annotation>