<annotation>
	<folder>training</folder>
	<filename>3248.jpg</filename>
	<path>/home/sdac_seminar/sdac_seminar_sose22/dataset/training/images/3248.jpg</path>
	<source>
		<database>Source</database>
	</source>
	<segmented>0</segmented>
	<size>
		<width>1024</width>
		<height>1024</height>
		<depth>3</depth>
	</size>
	<object>
		<name>Gegensprechanlage_mit_Video</name>
		<pose>Front</pose>
		<truncated>0</truncated>
		<bndbox>
			<xmin>639</xmin>
			<ymin>189</ymin>
			<xmax>815</xmax>
			<ymax>284</ymax>
		</bndbox>
	</object>
	<object>
		<name>Datenanschluss_einfach</name>
		<pose>Front</pose>
		<truncated>0</truncated>
		<bndbox>
			<xmin>251</xmin>
			<ymin>516</ymin>
			<xmax>368</xmax>
			<ymax>638</ymax>
		</bndbox>
	</object>
	<object>
		<name>Gegensprechanlage_mit_Video</name>
		<pose>Front</pose>
		<truncated>0</truncated>
		<bndbox>
			<xmin>118</xmin>
			<ymin>769</ymin>
			<xmax>206</xmax>
			<ymax>816</ymax>
		</bndbox>
	</object>
	<object>
		<name>Datenanschluss_einfach</name>
		<pose>Front</pose>
		<truncated>0</truncated>
		<bndbox>
			<xmin>521</xmin>
			<ymin>262</ymin>
			<xmax>590</xmax>
			<ymax>362</ymax>
		</bndbox>
	</object>
</annotation>