<annotation>
	<folder>training</folder>
	<filename>327.jpg</filename>
	<path>/home/sdac_seminar/sdac_seminar_sose22/dataset/training/images/327.jpg</path>
	<source>
		<database>Source</database>
	</source>
	<segmented>0</segmented>
	<size>
		<width>1024</width>
		<height>1024</height>
		<depth>3</depth>
	</size>
	<object>
		<name>RMO_Rauchmelder_optischer</name>
		<pose>Front</pose>
		<truncated>0</truncated>
		<bndbox>
			<xmin>506</xmin>
			<ymin>609</ymin>
			<xmax>619</xmax>
			<ymax>722</ymax>
		</bndbox>
	</object>
	<object>
		<name>Datenanschluss_zweifach</name>
		<pose>Front</pose>
		<truncated>0</truncated>
		<bndbox>
			<xmin>860</xmin>
			<ymin>272</ymin>
			<xmax>963</xmax>
			<ymax>341</ymax>
		</bndbox>
	</object>
	<object>
		<name>Taster_beleuchtet</name>
		<pose>Front</pose>
		<truncated>0</truncated>
		<bndbox>
			<xmin>137</xmin>
			<ymin>549</ymin>
			<xmax>231</xmax>
			<ymax>643</ymax>
		</bndbox>
	</object>
	<object>
		<name>KFO_Kamera_mit_Festobjektiv</name>
		<pose>Front</pose>
		<truncated>0</truncated>
		<bndbox>
			<xmin>765</xmin>
			<ymin>385</ymin>
			<xmax>971</xmax>
			<ymax>569</ymax>
		</bndbox>
	</object>
	<object>
		<name>Ausschalter_beleuchtet</name>
		<pose>Front</pose>
		<truncated>0</truncated>
		<bndbox>
			<xmin>633</xmin>
			<ymin>451</ymin>
			<xmax>745</xmax>
			<ymax>547</ymax>
		</bndbox>
	</object>
</annotation>