<annotation>
	<folder>training</folder>
	<filename>3312.jpg</filename>
	<path>/home/sdac_seminar/sdac_seminar_sose22/dataset/training/images/3312.jpg</path>
	<source>
		<database>Source</database>
	</source>
	<segmented>0</segmented>
	<size>
		<width>1024</width>
		<height>1024</height>
		<depth>3</depth>
	</size>
	<object>
		<name>NAM-Nichtautomatischer_Melder</name>
		<pose>Front</pose>
		<truncated>0</truncated>
		<bndbox>
			<xmin>746</xmin>
			<ymin>97</ymin>
			<xmax>878</xmax>
			<ymax>229</ymax>
		</bndbox>
	</object>
	<object>
		<name>Downlight_LED_Einbauleuchten_Flur</name>
		<pose>Front</pose>
		<truncated>0</truncated>
		<bndbox>
			<xmin>386</xmin>
			<ymin>546</ymin>
			<xmax>450</xmax>
			<ymax>592</ymax>
		</bndbox>
	</object>
	<object>
		<name>NAM-Nichtautomatischer_Melder</name>
		<pose>Front</pose>
		<truncated>0</truncated>
		<bndbox>
			<xmin>154</xmin>
			<ymin>719</ymin>
			<xmax>214</xmax>
			<ymax>779</ymax>
		</bndbox>
	</object>
	<object>
		<name>Wechselschalter</name>
		<pose>Front</pose>
		<truncated>0</truncated>
		<bndbox>
			<xmin>880</xmin>
			<ymin>326</ymin>
			<xmax>986</xmax>
			<ymax>434</ymax>
		</bndbox>
	</object>
	<object>
		<name>NAM-Nichtautomatischer_Melder</name>
		<pose>Front</pose>
		<truncated>0</truncated>
		<bndbox>
			<xmin>307</xmin>
			<ymin>802</ymin>
			<xmax>439</xmax>
			<ymax>934</ymax>
		</bndbox>
	</object>
	<object>
		<name>NAM-Nichtautomatischer_Melder</name>
		<pose>Front</pose>
		<truncated>0</truncated>
		<bndbox>
			<xmin>406</xmin>
			<ymin>163</ymin>
			<xmax>519</xmax>
			<ymax>276</ymax>
		</bndbox>
	</object>
	<object>
		<name>NAM-Nichtautomatischer_Melder</name>
		<pose>Front</pose>
		<truncated>0</truncated>
		<bndbox>
			<xmin>881</xmin>
			<ymin>340</ymin>
			<xmax>947</xmax>
			<ymax>406</ymax>
		</bndbox>
	</object>
</annotation>