<annotation>
	<folder>training</folder>
	<filename>3550.jpg</filename>
	<path>/home/sdac_seminar/sdac_seminar_sose22/dataset/training/images/3550.jpg</path>
	<source>
		<database>Source</database>
	</source>
	<segmented>0</segmented>
	<size>
		<width>1024</width>
		<height>1024</height>
		<depth>3</depth>
	</size>
	<object>
		<name>Wechselschalter</name>
		<pose>Front</pose>
		<truncated>0</truncated>
		<bndbox>
			<xmin>538</xmin>
			<ymin>128</ymin>
			<xmax>610</xmax>
			<ymax>206</ymax>
		</bndbox>
	</object>
	<object>
		<name>Wechselschalter</name>
		<pose>Front</pose>
		<truncated>0</truncated>
		<bndbox>
			<xmin>193</xmin>
			<ymin>490</ymin>
			<xmax>265</xmax>
			<ymax>568</ymax>
		</bndbox>
	</object>
</annotation>