<annotation>
	<folder>training</folder>
	<filename>4182.jpg</filename>
	<path>/home/sdac_seminar/sdac_seminar_sose22/dataset/training/images/4182.jpg</path>
	<source>
		<database>Source</database>
	</source>
	<segmented>0</segmented>
	<size>
		<width>1024</width>
		<height>1024</height>
		<depth>3</depth>
	</size>
	<object>
		<name>OKW_Multisensormelder_(Kombination_optischer_Rauch-Kahlenmonoxid_Waerme-Melder)</name>
		<pose>Front</pose>
		<truncated>0</truncated>
		<bndbox>
			<xmin>630</xmin>
			<ymin>132</ymin>
			<xmax>716</xmax>
			<ymax>218</ymax>
		</bndbox>
	</object>
	<object>
		<name>Gegensprechanlage_mit_Video</name>
		<pose>Front</pose>
		<truncated>0</truncated>
		<bndbox>
			<xmin>143</xmin>
			<ymin>796</ymin>
			<xmax>200</xmax>
			<ymax>890</ymax>
		</bndbox>
	</object>
	<object>
		<name>KFO_Kamera_mit_Festobjektiv</name>
		<pose>Front</pose>
		<truncated>0</truncated>
		<bndbox>
			<xmin>85</xmin>
			<ymin>380</ymin>
			<xmax>239</xmax>
			<ymax>562</ymax>
		</bndbox>
	</object>
	<object>
		<name>Elektroanschluss_allgemein_230V_Geraeteanschlussdose_230V</name>
		<pose>Front</pose>
		<truncated>0</truncated>
		<bndbox>
			<xmin>345</xmin>
			<ymin>70</ymin>
			<xmax>392</xmax>
			<ymax>119</ymax>
		</bndbox>
	</object>
	<object>
		<name>KFO_Kamera_mit_Festobjektiv</name>
		<pose>Front</pose>
		<truncated>0</truncated>
		<bndbox>
			<xmin>306</xmin>
			<ymin>734</ymin>
			<xmax>546</xmax>
			<ymax>968</ymax>
		</bndbox>
	</object>
</annotation>