<annotation>
	<folder>training</folder>
	<filename>4194.jpg</filename>
	<path>/home/sdac_seminar/sdac_seminar_sose22/dataset/training/images/4194.jpg</path>
	<source>
		<database>Source</database>
	</source>
	<segmented>0</segmented>
	<size>
		<width>1024</width>
		<height>1024</height>
		<depth>3</depth>
	</size>
	<object>
		<name>Zugtaster</name>
		<pose>Front</pose>
		<truncated>0</truncated>
		<bndbox>
			<xmin>319</xmin>
			<ymin>728</ymin>
			<xmax>463</xmax>
			<ymax>972</ymax>
		</bndbox>
	</object>
	<object>
		<name>WLAN</name>
		<pose>Front</pose>
		<truncated>0</truncated>
		<bndbox>
			<xmin>398</xmin>
			<ymin>896</ymin>
			<xmax>466</xmax>
			<ymax>964</ymax>
		</bndbox>
	</object>
	<object>
		<name>Zimmersignalleuchte</name>
		<pose>Front</pose>
		<truncated>0</truncated>
		<bndbox>
			<xmin>739</xmin>
			<ymin>484</ymin>
			<xmax>935</xmax>
			<ymax>684</ymax>
		</bndbox>
	</object>
	<object>
		<name>RMO_Rauchmelder_optischer</name>
		<pose>Front</pose>
		<truncated>0</truncated>
		<bndbox>
			<xmin>506</xmin>
			<ymin>126</ymin>
			<xmax>562</xmax>
			<ymax>182</ymax>
		</bndbox>
	</object>
</annotation>