<annotation>
	<folder>training</folder>
	<filename>4312.jpg</filename>
	<path>/home/sdac_seminar/sdac_seminar_sose22/dataset/training/images/4312.jpg</path>
	<source>
		<database>Source</database>
	</source>
	<segmented>0</segmented>
	<size>
		<width>1024</width>
		<height>1024</height>
		<depth>3</depth>
	</size>
	<object>
		<name>Wechselschalter</name>
		<pose>Front</pose>
		<truncated>0</truncated>
		<bndbox>
			<xmin>631</xmin>
			<ymin>160</ymin>
			<xmax>838</xmax>
			<ymax>372</ymax>
		</bndbox>
	</object>
	<object>
		<name>ROA_Rauchmelder_optisch_mit_Signalgeber_(Sockelsirene)</name>
		<pose>Front</pose>
		<truncated>0</truncated>
		<bndbox>
			<xmin>437</xmin>
			<ymin>166</ymin>
			<xmax>562</xmax>
			<ymax>291</ymax>
		</bndbox>
	</object>
</annotation>