<annotation>
	<folder>training</folder>
	<filename>4362.jpg</filename>
	<path>/home/sdac_seminar/sdac_seminar_sose22/dataset/training/images/4362.jpg</path>
	<source>
		<database>Source</database>
	</source>
	<segmented>0</segmented>
	<size>
		<width>1024</width>
		<height>1024</height>
		<depth>3</depth>
	</size>
	<object>
		<name>Ausschalter_beleuchtet</name>
		<pose>Front</pose>
		<truncated>0</truncated>
		<bndbox>
			<xmin>171</xmin>
			<ymin>338</ymin>
			<xmax>283</xmax>
			<ymax>434</ymax>
		</bndbox>
	</object>
	<object>
		<name>NAM-Nichtautomatischer_Melder</name>
		<pose>Front</pose>
		<truncated>0</truncated>
		<bndbox>
			<xmin>297</xmin>
			<ymin>751</ymin>
			<xmax>429</xmax>
			<ymax>883</ymax>
		</bndbox>
	</object>
	<object>
		<name>WLAN</name>
		<pose>Front</pose>
		<truncated>0</truncated>
		<bndbox>
			<xmin>705</xmin>
			<ymin>136</ymin>
			<xmax>757</xmax>
			<ymax>188</ymax>
		</bndbox>
	</object>
	<object>
		<name>Datenanschluss_einfach</name>
		<pose>Front</pose>
		<truncated>0</truncated>
		<bndbox>
			<xmin>851</xmin>
			<ymin>871</ymin>
			<xmax>951</xmax>
			<ymax>940</ymax>
		</bndbox>
	</object>
	<object>
		<name>WLAN</name>
		<pose>Front</pose>
		<truncated>0</truncated>
		<bndbox>
			<xmin>845</xmin>
			<ymin>467</ymin>
			<xmax>993</xmax>
			<ymax>614</ymax>
		</bndbox>
	</object>
	<object>
		<name>Zimmersignalleuchte</name>
		<pose>Front</pose>
		<truncated>0</truncated>
		<bndbox>
			<xmin>852</xmin>
			<ymin>364</ymin>
			<xmax>982</xmax>
			<ymax>494</ymax>
		</bndbox>
	</object>
	<object>
		<name>Zimmersignalleuchte</name>
		<pose>Front</pose>
		<truncated>0</truncated>
		<bndbox>
			<xmin>171</xmin>
			<ymin>343</ymin>
			<xmax>371</xmax>
			<ymax>539</ymax>
		</bndbox>
	</object>
</annotation>