<annotation>
	<folder>training</folder>
	<filename>4619.jpg</filename>
	<path>/home/sdac_seminar/sdac_seminar_sose22/dataset/training/images/4619.jpg</path>
	<source>
		<database>Source</database>
	</source>
	<segmented>0</segmented>
	<size>
		<width>1024</width>
		<height>1024</height>
		<depth>3</depth>
	</size>
	<object>
		<name>Schukosteckdose_einfach</name>
		<pose>Front</pose>
		<truncated>0</truncated>
		<bndbox>
			<xmin>540</xmin>
			<ymin>779</ymin>
			<xmax>583</xmax>
			<ymax>829</ymax>
		</bndbox>
	</object>
	<object>
		<name>Datenanschluss_zweifach</name>
		<pose>Front</pose>
		<truncated>0</truncated>
		<bndbox>
			<xmin>847</xmin>
			<ymin>655</ymin>
			<xmax>950</xmax>
			<ymax>724</ymax>
		</bndbox>
	</object>
	<object>
		<name>WLAN</name>
		<pose>Front</pose>
		<truncated>0</truncated>
		<bndbox>
			<xmin>144</xmin>
			<ymin>562</ymin>
			<xmax>248</xmax>
			<ymax>667</ymax>
		</bndbox>
	</object>
	<object>
		<name>Serienschalter</name>
		<pose>Front</pose>
		<truncated>0</truncated>
		<bndbox>
			<xmin>330</xmin>
			<ymin>809</ymin>
			<xmax>414</xmax>
			<ymax>857</ymax>
		</bndbox>
	</object>
	<object>
		<name>Downlight_LED_Einbauleuchten_Flur</name>
		<pose>Front</pose>
		<truncated>0</truncated>
		<bndbox>
			<xmin>556</xmin>
			<ymin>436</ymin>
			<xmax>602</xmax>
			<ymax>500</ymax>
		</bndbox>
	</object>
	<object>
		<name>Schukosteckdose_einfach</name>
		<pose>Front</pose>
		<truncated>0</truncated>
		<bndbox>
			<xmin>889</xmin>
			<ymin>352</ymin>
			<xmax>939</xmax>
			<ymax>395</ymax>
		</bndbox>
	</object>
	<object>
		<name>Schukosteckdose_einfach</name>
		<pose>Front</pose>
		<truncated>0</truncated>
		<bndbox>
			<xmin>552</xmin>
			<ymin>791</ymin>
			<xmax>663</xmax>
			<ymax>911</ymax>
		</bndbox>
	</object>
</annotation>