<annotation>
	<folder>training</folder>
	<filename>5053.jpg</filename>
	<path>/home/sdac_seminar/sdac_seminar_sose22/dataset/training/images/5053.jpg</path>
	<source>
		<database>Source</database>
	</source>
	<segmented>0</segmented>
	<size>
		<width>1024</width>
		<height>1024</height>
		<depth>3</depth>
	</size>
	<object>
		<name>Downlight_LED_Einbauleuchten_Flur</name>
		<pose>Front</pose>
		<truncated>0</truncated>
		<bndbox>
			<xmin>223</xmin>
			<ymin>519</ymin>
			<xmax>269</xmax>
			<ymax>583</ymax>
		</bndbox>
	</object>
	<object>
		<name>ASR_Ansaugrauchmelder</name>
		<pose>Front</pose>
		<truncated>0</truncated>
		<bndbox>
			<xmin>721</xmin>
			<ymin>374</ymin>
			<xmax>898</xmax>
			<ymax>551</ymax>
		</bndbox>
	</object>
	<object>
		<name>OKW_Multisensormelder_(Kombination_optischer_Rauch-Kahlenmonoxid_Waerme-Melder)</name>
		<pose>Front</pose>
		<truncated>0</truncated>
		<bndbox>
			<xmin>516</xmin>
			<ymin>851</ymin>
			<xmax>648</xmax>
			<ymax>983</ymax>
		</bndbox>
	</object>
	<object>
		<name>Downlight_LED_Einbauleuchten_Flur</name>
		<pose>Front</pose>
		<truncated>0</truncated>
		<bndbox>
			<xmin>480</xmin>
			<ymin>480</ymin>
			<xmax>573</xmax>
			<ymax>608</ymax>
		</bndbox>
	</object>
	<object>
		<name>ASR_Ansaugrauchmelder</name>
		<pose>Front</pose>
		<truncated>0</truncated>
		<bndbox>
			<xmin>757</xmin>
			<ymin>130</ymin>
			<xmax>819</xmax>
			<ymax>192</ymax>
		</bndbox>
	</object>
</annotation>