<annotation>
	<folder>training</folder>
	<filename>507.jpg</filename>
	<path>/home/sdac_seminar/sdac_seminar_sose22/dataset/training/images/507.jpg</path>
	<source>
		<database>Source</database>
	</source>
	<segmented>0</segmented>
	<size>
		<width>1024</width>
		<height>1024</height>
		<depth>3</depth>
	</size>
	<object>
		<name>Ausschalter_beleuchtet</name>
		<pose>Front</pose>
		<truncated>0</truncated>
		<bndbox>
			<xmin>321</xmin>
			<ymin>773</ymin>
			<xmax>417</xmax>
			<ymax>885</ymax>
		</bndbox>
	</object>
	<object>
		<name>NAM-Nichtautomatischer_Melder</name>
		<pose>Front</pose>
		<truncated>0</truncated>
		<bndbox>
			<xmin>569</xmin>
			<ymin>717</ymin>
			<xmax>682</xmax>
			<ymax>830</ymax>
		</bndbox>
	</object>
	<object>
		<name>ASR_Ansaugoeffnung</name>
		<pose>Front</pose>
		<truncated>0</truncated>
		<bndbox>
			<xmin>234</xmin>
			<ymin>497</ymin>
			<xmax>257</xmax>
			<ymax>585</ymax>
		</bndbox>
	</object>
	<object>
		<name>Ausschalter_beleuchtet</name>
		<pose>Front</pose>
		<truncated>0</truncated>
		<bndbox>
			<xmin>422</xmin>
			<ymin>209</ymin>
			<xmax>518</xmax>
			<ymax>321</ymax>
		</bndbox>
	</object>
	<object>
		<name>ASR_Ansaugoeffnung</name>
		<pose>Front</pose>
		<truncated>0</truncated>
		<bndbox>
			<xmin>652</xmin>
			<ymin>542</ymin>
			<xmax>834</xmax>
			<ymax>624</ymax>
		</bndbox>
	</object>
</annotation>