<annotation>
	<folder>training</folder>
	<filename>5448.jpg</filename>
	<path>/home/sdac_seminar/sdac_seminar_sose22/dataset/training/images/5448.jpg</path>
	<source>
		<database>Source</database>
	</source>
	<segmented>0</segmented>
	<size>
		<width>1024</width>
		<height>1024</height>
		<depth>3</depth>
	</size>
	<object>
		<name>Gegensprechanlage_mit_Video</name>
		<pose>Front</pose>
		<truncated>0</truncated>
		<bndbox>
			<xmin>876</xmin>
			<ymin>639</ymin>
			<xmax>1024</xmax>
			<ymax>833</ymax>
		</bndbox>
	</object>
	<object>
		<name>Zugtaster</name>
		<pose>Front</pose>
		<truncated>0</truncated>
		<bndbox>
			<xmin>336</xmin>
			<ymin>132</ymin>
			<xmax>430</xmax>
			<ymax>266</ymax>
		</bndbox>
	</object>
	<object>
		<name>NAM-Nichtautomatischer_Melder</name>
		<pose>Front</pose>
		<truncated>0</truncated>
		<bndbox>
			<xmin>165</xmin>
			<ymin>545</ymin>
			<xmax>278</xmax>
			<ymax>658</ymax>
		</bndbox>
	</object>
	<object>
		<name>Gegensprechanlage_mit_Video</name>
		<pose>Front</pose>
		<truncated>0</truncated>
		<bndbox>
			<xmin>716</xmin>
			<ymin>87</ymin>
			<xmax>892</xmax>
			<ymax>182</ymax>
		</bndbox>
	</object>
	<object>
		<name>Zugtaster</name>
		<pose>Front</pose>
		<truncated>0</truncated>
		<bndbox>
			<xmin>343</xmin>
			<ymin>458</ymin>
			<xmax>487</xmax>
			<ymax>702</ymax>
		</bndbox>
	</object>
</annotation>