<annotation>
	<folder>training</folder>
	<filename>5475.jpg</filename>
	<path>/home/sdac_seminar/sdac_seminar_sose22/dataset/training/images/5475.jpg</path>
	<source>
		<database>Source</database>
	</source>
	<segmented>0</segmented>
	<size>
		<width>1024</width>
		<height>1024</height>
		<depth>3</depth>
	</size>
	<object>
		<name>Zimmersignalleuchte</name>
		<pose>Front</pose>
		<truncated>0</truncated>
		<bndbox>
			<xmin>86</xmin>
			<ymin>127</ymin>
			<xmax>184</xmax>
			<ymax>227</ymax>
		</bndbox>
	</object>
	<object>
		<name>NAM-Nichtautomatischer_Melder</name>
		<pose>Front</pose>
		<truncated>0</truncated>
		<bndbox>
			<xmin>57</xmin>
			<ymin>486</ymin>
			<xmax>214</xmax>
			<ymax>643</ymax>
		</bndbox>
	</object>
	<object>
		<name>Einbaudownlights_LED_Konferenzraeume</name>
		<pose>Front</pose>
		<truncated>0</truncated>
		<bndbox>
			<xmin>801</xmin>
			<ymin>262</ymin>
			<xmax>905</xmax>
			<ymax>412</ymax>
		</bndbox>
	</object>
	<object>
		<name>NAM-Nichtautomatischer_Melder</name>
		<pose>Front</pose>
		<truncated>0</truncated>
		<bndbox>
			<xmin>158</xmin>
			<ymin>701</ymin>
			<xmax>224</xmax>
			<ymax>767</ymax>
		</bndbox>
	</object>
	<object>
		<name>NAM-Nichtautomatischer_Melder</name>
		<pose>Front</pose>
		<truncated>0</truncated>
		<bndbox>
			<xmin>90</xmin>
			<ymin>50</ymin>
			<xmax>166</xmax>
			<ymax>126</ymax>
		</bndbox>
	</object>
</annotation>