<annotation>
	<folder>training</folder>
	<filename>5759.jpg</filename>
	<path>/home/sdac_seminar/sdac_seminar_sose22/dataset/training/images/5759.jpg</path>
	<source>
		<database>Source</database>
	</source>
	<segmented>0</segmented>
	<size>
		<width>1024</width>
		<height>1024</height>
		<depth>3</depth>
	</size>
	<object>
		<name>Datenanschluss_einfach</name>
		<pose>Front</pose>
		<truncated>0</truncated>
		<bndbox>
			<xmin>578</xmin>
			<ymin>724</ymin>
			<xmax>630</xmax>
			<ymax>784</ymax>
		</bndbox>
	</object>
	<object>
		<name>OT_Multisensormelder_(Kombination_RMO_WMD)</name>
		<pose>Front</pose>
		<truncated>0</truncated>
		<bndbox>
			<xmin>699</xmin>
			<ymin>200</ymin>
			<xmax>777</xmax>
			<ymax>278</ymax>
		</bndbox>
	</object>
	<object>
		<name>Datenanschluss_einfach</name>
		<pose>Front</pose>
		<truncated>0</truncated>
		<bndbox>
			<xmin>449</xmin>
			<ymin>257</ymin>
			<xmax>499</xmax>
			<ymax>291</ymax>
		</bndbox>
	</object>
	<object>
		<name>ROA_Rauchmelder_optisch_mit_Signalgeber_(Sockelsirene)</name>
		<pose>Front</pose>
		<truncated>0</truncated>
		<bndbox>
			<xmin>139</xmin>
			<ymin>237</ymin>
			<xmax>195</xmax>
			<ymax>293</ymax>
		</bndbox>
	</object>
	<object>
		<name>Datenanschluss_einfach</name>
		<pose>Front</pose>
		<truncated>0</truncated>
		<bndbox>
			<xmin>196</xmin>
			<ymin>397</ymin>
			<xmax>246</xmax>
			<ymax>431</ymax>
		</bndbox>
	</object>
	<object>
		<name>OT_Multisensormelder_(Kombination_RMO_WMD)</name>
		<pose>Front</pose>
		<truncated>0</truncated>
		<bndbox>
			<xmin>825</xmin>
			<ymin>776</ymin>
			<xmax>938</xmax>
			<ymax>889</ymax>
		</bndbox>
	</object>
	<object>
		<name>ROA_Rauchmelder_optisch_mit_Signalgeber_(Sockelsirene)</name>
		<pose>Front</pose>
		<truncated>0</truncated>
		<bndbox>
			<xmin>699</xmin>
			<ymin>79</ymin>
			<xmax>775</xmax>
			<ymax>155</ymax>
		</bndbox>
	</object>
	<object>
		<name>OT_Multisensormelder_(Kombination_RMO_WMD)</name>
		<pose>Front</pose>
		<truncated>0</truncated>
		<bndbox>
			<xmin>710</xmin>
			<ymin>82</ymin>
			<xmax>766</xmax>
			<ymax>138</ymax>
		</bndbox>
	</object>
</annotation>