<annotation>
	<folder>training</folder>
	<filename>5840.jpg</filename>
	<path>/home/sdac_seminar/sdac_seminar_sose22/dataset/training/images/5840.jpg</path>
	<source>
		<database>Source</database>
	</source>
	<segmented>0</segmented>
	<size>
		<width>1024</width>
		<height>1024</height>
		<depth>3</depth>
	</size>
	<object>
		<name>Elektroanschluss_allgemein_230V_Geraeteanschlussdose_230V</name>
		<pose>Front</pose>
		<truncated>0</truncated>
		<bndbox>
			<xmin>273</xmin>
			<ymin>825</ymin>
			<xmax>372</xmax>
			<ymax>919</ymax>
		</bndbox>
	</object>
	<object>
		<name>ROA_Rauchmelder_optisch_mit_Signalgeber_(Sockelsirene)</name>
		<pose>Front</pose>
		<truncated>0</truncated>
		<bndbox>
			<xmin>161</xmin>
			<ymin>310</ymin>
			<xmax>280</xmax>
			<ymax>429</ymax>
		</bndbox>
	</object>
	<object>
		<name>ROA_Rauchmelder_optisch_mit_Signalgeber_(Sockelsirene)</name>
		<pose>Front</pose>
		<truncated>0</truncated>
		<bndbox>
			<xmin>107</xmin>
			<ymin>592</ymin>
			<xmax>220</xmax>
			<ymax>705</ymax>
		</bndbox>
	</object>
</annotation>