<annotation>
	<folder>training</folder>
	<filename>6358.jpg</filename>
	<path>/home/sdac_seminar/sdac_seminar_sose22/dataset/training/images/6358.jpg</path>
	<source>
		<database>Source</database>
	</source>
	<segmented>0</segmented>
	<size>
		<width>1024</width>
		<height>1024</height>
		<depth>3</depth>
	</size>
	<object>
		<name>KFO_Kamera_mit_Festobjektiv</name>
		<pose>Front</pose>
		<truncated>0</truncated>
		<bndbox>
			<xmin>782</xmin>
			<ymin>638</ymin>
			<xmax>936</xmax>
			<ymax>820</ymax>
		</bndbox>
	</object>
	<object>
		<name>Schukosteckdose_einfach</name>
		<pose>Front</pose>
		<truncated>0</truncated>
		<bndbox>
			<xmin>424</xmin>
			<ymin>179</ymin>
			<xmax>524</xmax>
			<ymax>266</ymax>
		</bndbox>
	</object>
	<object>
		<name>Taster_beleuchtet</name>
		<pose>Front</pose>
		<truncated>0</truncated>
		<bndbox>
			<xmin>156</xmin>
			<ymin>321</ymin>
			<xmax>222</xmax>
			<ymax>387</ymax>
		</bndbox>
	</object>
	<object>
		<name>Schukosteckdose_einfach</name>
		<pose>Front</pose>
		<truncated>0</truncated>
		<bndbox>
			<xmin>608</xmin>
			<ymin>816</ymin>
			<xmax>740</xmax>
			<ymax>949</ymax>
		</bndbox>
	</object>
</annotation>