<annotation>
	<folder>training</folder>
	<filename>6482.jpg</filename>
	<path>/home/sdac_seminar/sdac_seminar_sose22/dataset/training/images/6482.jpg</path>
	<source>
		<database>Source</database>
	</source>
	<segmented>0</segmented>
	<size>
		<width>1024</width>
		<height>1024</height>
		<depth>3</depth>
	</size>
	<object>
		<name>Schukosteckdose_einfach</name>
		<pose>Front</pose>
		<truncated>0</truncated>
		<bndbox>
			<xmin>555</xmin>
			<ymin>132</ymin>
			<xmax>598</xmax>
			<ymax>182</ymax>
		</bndbox>
	</object>
	<object>
		<name>Downlight_LED_Einbauleuchten_Flur</name>
		<pose>Front</pose>
		<truncated>0</truncated>
		<bndbox>
			<xmin>50</xmin>
			<ymin>325</ymin>
			<xmax>128</xmax>
			<ymax>395</ymax>
		</bndbox>
	</object>
	<object>
		<name>Schukosteckdose_einfach</name>
		<pose>Front</pose>
		<truncated>0</truncated>
		<bndbox>
			<xmin>212</xmin>
			<ymin>822</ymin>
			<xmax>312</xmax>
			<ymax>909</ymax>
		</bndbox>
	</object>
</annotation>