<annotation>
	<folder>training</folder>
	<filename>6701.jpg</filename>
	<path>/home/sdac_seminar/sdac_seminar_sose22/dataset/training/images/6701.jpg</path>
	<source>
		<database>Source</database>
	</source>
	<segmented>0</segmented>
	<size>
		<width>1024</width>
		<height>1024</height>
		<depth>3</depth>
	</size>
	<object>
		<name>Downlight_LED_Einbauleuchten_Flur</name>
		<pose>Front</pose>
		<truncated>0</truncated>
		<bndbox>
			<xmin>256</xmin>
			<ymin>234</ymin>
			<xmax>328</xmax>
			<ymax>314</ymax>
		</bndbox>
	</object>
	<object>
		<name>Scheinwerfer_fuer_Alarmbeleuchtung</name>
		<pose>Front</pose>
		<truncated>0</truncated>
		<bndbox>
			<xmin>502</xmin>
			<ymin>566</ymin>
			<xmax>634</xmax>
			<ymax>678</ymax>
		</bndbox>
	</object>
	<object>
		<name>Elektroanschluss_allgemein_230V_Geraeteanschlussdose_230V</name>
		<pose>Front</pose>
		<truncated>0</truncated>
		<bndbox>
			<xmin>910</xmin>
			<ymin>327</ymin>
			<xmax>959</xmax>
			<ymax>374</ymax>
		</bndbox>
	</object>
	<object>
		<name>ASR_Ansaugrauchmelder</name>
		<pose>Front</pose>
		<truncated>0</truncated>
		<bndbox>
			<xmin>805</xmin>
			<ymin>659</ymin>
			<xmax>877</xmax>
			<ymax>731</ymax>
		</bndbox>
	</object>
	<object>
		<name>Scheinwerfer_fuer_Alarmbeleuchtung</name>
		<pose>Front</pose>
		<truncated>0</truncated>
		<bndbox>
			<xmin>521</xmin>
			<ymin>442</ymin>
			<xmax>691</xmax>
			<ymax>604</ymax>
		</bndbox>
	</object>
	<object>
		<name>Elektroanschluss_allgemein_230V_Geraeteanschlussdose_230V</name>
		<pose>Front</pose>
		<truncated>0</truncated>
		<bndbox>
			<xmin>678</xmin>
			<ymin>491</ymin>
			<xmax>725</xmax>
			<ymax>540</ymax>
		</bndbox>
	</object>
	<object>
		<name>Scheinwerfer_fuer_Alarmbeleuchtung</name>
		<pose>Front</pose>
		<truncated>0</truncated>
		<bndbox>
			<xmin>820</xmin>
			<ymin>669</ymin>
			<xmax>1024</xmax>
			<ymax>933</ymax>
		</bndbox>
	</object>
</annotation>