<annotation>
	<folder>training</folder>
	<filename>6905.jpg</filename>
	<path>/home/sdac_seminar/sdac_seminar_sose22/dataset/training/images/6905.jpg</path>
	<source>
		<database>Source</database>
	</source>
	<segmented>0</segmented>
	<size>
		<width>1024</width>
		<height>1024</height>
		<depth>3</depth>
	</size>
	<object>
		<name>Ausschalter_beleuchtet</name>
		<pose>Front</pose>
		<truncated>0</truncated>
		<bndbox>
			<xmin>120</xmin>
			<ymin>537</ymin>
			<xmax>216</xmax>
			<ymax>649</ymax>
		</bndbox>
	</object>
	<object>
		<name>NAM-Nichtautomatischer_Melder</name>
		<pose>Front</pose>
		<truncated>0</truncated>
		<bndbox>
			<xmin>111</xmin>
			<ymin>192</ymin>
			<xmax>285</xmax>
			<ymax>366</ymax>
		</bndbox>
	</object>
	<object>
		<name>Gegensprechanlage_mit_Video</name>
		<pose>Front</pose>
		<truncated>0</truncated>
		<bndbox>
			<xmin>854</xmin>
			<ymin>56</ymin>
			<xmax>1024</xmax>
			<ymax>226</ymax>
		</bndbox>
	</object>
	<object>
		<name>Ausschalter_beleuchtet</name>
		<pose>Front</pose>
		<truncated>0</truncated>
		<bndbox>
			<xmin>415</xmin>
			<ymin>496</ymin>
			<xmax>527</xmax>
			<ymax>592</ymax>
		</bndbox>
	</object>
	<object>
		<name>NAM-Nichtautomatischer_Melder</name>
		<pose>Front</pose>
		<truncated>0</truncated>
		<bndbox>
			<xmin>815</xmin>
			<ymin>612</ymin>
			<xmax>901</xmax>
			<ymax>698</ymax>
		</bndbox>
	</object>
</annotation>