<annotation>
	<folder>training</folder>
	<filename>7121.jpg</filename>
	<path>/home/sdac_seminar/sdac_seminar_sose22/dataset/training/images/7121.jpg</path>
	<source>
		<database>Source</database>
	</source>
	<segmented>0</segmented>
	<size>
		<width>1024</width>
		<height>1024</height>
		<depth>3</depth>
	</size>
	<object>
		<name>Schukosteckdose_einfach</name>
		<pose>Front</pose>
		<truncated>0</truncated>
		<bndbox>
			<xmin>621</xmin>
			<ymin>204</ymin>
			<xmax>664</xmax>
			<ymax>254</ymax>
		</bndbox>
	</object>
	<object>
		<name>NAM-Nichtautomatischer_Melder</name>
		<pose>Front</pose>
		<truncated>0</truncated>
		<bndbox>
			<xmin>94</xmin>
			<ymin>160</ymin>
			<xmax>239</xmax>
			<ymax>305</ymax>
		</bndbox>
	</object>
	<object>
		<name>Wechselschalter</name>
		<pose>Front</pose>
		<truncated>0</truncated>
		<bndbox>
			<xmin>172</xmin>
			<ymin>379</ymin>
			<xmax>264</xmax>
			<ymax>465</ymax>
		</bndbox>
	</object>
	<object>
		<name>Wechselschalter</name>
		<pose>Front</pose>
		<truncated>0</truncated>
		<bndbox>
			<xmin>713</xmin>
			<ymin>139</ymin>
			<xmax>785</xmax>
			<ymax>217</ymax>
		</bndbox>
	</object>
</annotation>