<annotation>
	<folder>training</folder>
	<filename>7195.jpg</filename>
	<path>/home/sdac_seminar/sdac_seminar_sose22/dataset/training/images/7195.jpg</path>
	<source>
		<database>Source</database>
	</source>
	<segmented>0</segmented>
	<size>
		<width>1024</width>
		<height>1024</height>
		<depth>3</depth>
	</size>
	<object>
		<name>Ausschalter_beleuchtet</name>
		<pose>Front</pose>
		<truncated>0</truncated>
		<bndbox>
			<xmin>519</xmin>
			<ymin>596</ymin>
			<xmax>667</xmax>
			<ymax>744</ymax>
		</bndbox>
	</object>
	<object>
		<name>NAM-Nichtautomatischer_Melder</name>
		<pose>Front</pose>
		<truncated>0</truncated>
		<bndbox>
			<xmin>165</xmin>
			<ymin>619</ymin>
			<xmax>241</xmax>
			<ymax>695</ymax>
		</bndbox>
	</object>
	<object>
		<name>NAM-Nichtautomatischer_Melder</name>
		<pose>Front</pose>
		<truncated>0</truncated>
		<bndbox>
			<xmin>171</xmin>
			<ymin>477</ymin>
			<xmax>308</xmax>
			<ymax>614</ymax>
		</bndbox>
	</object>
</annotation>