<annotation>
	<folder>training</folder>
	<filename>7298.jpg</filename>
	<path>/home/sdac_seminar/sdac_seminar_sose22/dataset/training/images/7298.jpg</path>
	<source>
		<database>Source</database>
	</source>
	<segmented>0</segmented>
	<size>
		<width>1024</width>
		<height>1024</height>
		<depth>3</depth>
	</size>
	<object>
		<name>NAM-Nichtautomatischer_Melder</name>
		<pose>Front</pose>
		<truncated>0</truncated>
		<bndbox>
			<xmin>290</xmin>
			<ymin>833</ymin>
			<xmax>346</xmax>
			<ymax>889</ymax>
		</bndbox>
	</object>
	<object>
		<name>WLAN</name>
		<pose>Front</pose>
		<truncated>0</truncated>
		<bndbox>
			<xmin>682</xmin>
			<ymin>249</ymin>
			<xmax>787</xmax>
			<ymax>353</ymax>
		</bndbox>
	</object>
	<object>
		<name>NAM-Nichtautomatischer_Melder</name>
		<pose>Front</pose>
		<truncated>0</truncated>
		<bndbox>
			<xmin>307</xmin>
			<ymin>577</ymin>
			<xmax>420</xmax>
			<ymax>690</ymax>
		</bndbox>
	</object>
	<object>
		<name>Gegensprechanlage_mit_Video</name>
		<pose>Front</pose>
		<truncated>0</truncated>
		<bndbox>
			<xmin>397</xmin>
			<ymin>139</ymin>
			<xmax>492</xmax>
			<ymax>201</ymax>
		</bndbox>
	</object>
	<object>
		<name>WLAN</name>
		<pose>Front</pose>
		<truncated>0</truncated>
		<bndbox>
			<xmin>576</xmin>
			<ymin>93</ymin>
			<xmax>715</xmax>
			<ymax>233</ymax>
		</bndbox>
	</object>
</annotation>