<annotation>
	<folder>training</folder>
	<filename>7742.jpg</filename>
	<path>/home/sdac_seminar/sdac_seminar_sose22/dataset/training/images/7742.jpg</path>
	<source>
		<database>Source</database>
	</source>
	<segmented>0</segmented>
	<size>
		<width>1024</width>
		<height>1024</height>
		<depth>3</depth>
	</size>
	<object>
		<name>Ausschalter_beleuchtet</name>
		<pose>Front</pose>
		<truncated>0</truncated>
		<bndbox>
			<xmin>597</xmin>
			<ymin>873</ymin>
			<xmax>667</xmax>
			<ymax>947</ymax>
		</bndbox>
	</object>
	<object>
		<name>Zimmersignalleuchte</name>
		<pose>Front</pose>
		<truncated>0</truncated>
		<bndbox>
			<xmin>79</xmin>
			<ymin>754</ymin>
			<xmax>279</xmax>
			<ymax>950</ymax>
		</bndbox>
	</object>
	<object>
		<name>Ausschalter_beleuchtet</name>
		<pose>Front</pose>
		<truncated>0</truncated>
		<bndbox>
			<xmin>409</xmin>
			<ymin>820</ymin>
			<xmax>521</xmax>
			<ymax>916</ymax>
		</bndbox>
	</object>
</annotation>