<annotation>
	<folder>training</folder>
	<filename>8160.jpg</filename>
	<path>/home/sdac_seminar/sdac_seminar_sose22/dataset/training/images/8160.jpg</path>
	<source>
		<database>Source</database>
	</source>
	<segmented>0</segmented>
	<size>
		<width>1024</width>
		<height>1024</height>
		<depth>3</depth>
	</size>
	<object>
		<name>ASR_Ansaugoeffnung</name>
		<pose>Front</pose>
		<truncated>0</truncated>
		<bndbox>
			<xmin>776</xmin>
			<ymin>571</ymin>
			<xmax>799</xmax>
			<ymax>659</ymax>
		</bndbox>
	</object>
	<object>
		<name>Wechselschalter</name>
		<pose>Front</pose>
		<truncated>0</truncated>
		<bndbox>
			<xmin>595</xmin>
			<ymin>714</ymin>
			<xmax>701</xmax>
			<ymax>822</ymax>
		</bndbox>
	</object>
	<object>
		<name>Wechselschalter</name>
		<pose>Front</pose>
		<truncated>0</truncated>
		<bndbox>
			<xmin>894</xmin>
			<ymin>822</ymin>
			<xmax>972</xmax>
			<ymax>894</ymax>
		</bndbox>
	</object>
</annotation>