<annotation>
	<folder>training</folder>
	<filename>8389.jpg</filename>
	<path>/home/sdac_seminar/sdac_seminar_sose22/dataset/training/images/8389.jpg</path>
	<source>
		<database>Source</database>
	</source>
	<segmented>0</segmented>
	<size>
		<width>1024</width>
		<height>1024</height>
		<depth>3</depth>
	</size>
	<object>
		<name>Ausschalter_beleuchtet</name>
		<pose>Front</pose>
		<truncated>0</truncated>
		<bndbox>
			<xmin>202</xmin>
			<ymin>475</ymin>
			<xmax>272</xmax>
			<ymax>547</ymax>
		</bndbox>
	</object>
	<object>
		<name>ASR_Ansaugrauchmelder</name>
		<pose>Front</pose>
		<truncated>0</truncated>
		<bndbox>
			<xmin>797</xmin>
			<ymin>239</ymin>
			<xmax>859</xmax>
			<ymax>301</ymax>
		</bndbox>
	</object>
	<object>
		<name>Downlight_LED_Einbauleuchten_Flur</name>
		<pose>Front</pose>
		<truncated>0</truncated>
		<bndbox>
			<xmin>93</xmin>
			<ymin>122</ymin>
			<xmax>186</xmax>
			<ymax>250</ymax>
		</bndbox>
	</object>
	<object>
		<name>Datenanschluss_einfach</name>
		<pose>Front</pose>
		<truncated>0</truncated>
		<bndbox>
			<xmin>747</xmin>
			<ymin>539</ymin>
			<xmax>847</xmax>
			<ymax>608</ymax>
		</bndbox>
	</object>
	<object>
		<name>NAM-Nichtautomatischer_Melder</name>
		<pose>Front</pose>
		<truncated>0</truncated>
		<bndbox>
			<xmin>592</xmin>
			<ymin>349</ymin>
			<xmax>778</xmax>
			<ymax>535</ymax>
		</bndbox>
	</object>
	<object>
		<name>Ausschalter_beleuchtet</name>
		<pose>Front</pose>
		<truncated>0</truncated>
		<bndbox>
			<xmin>576</xmin>
			<ymin>114</ymin>
			<xmax>624</xmax>
			<ymax>170</ymax>
		</bndbox>
	</object>
	<object>
		<name>Downlight_LED_Einbauleuchten_Flur</name>
		<pose>Front</pose>
		<truncated>0</truncated>
		<bndbox>
			<xmin>296</xmin>
			<ymin>371</ymin>
			<xmax>424</xmax>
			<ymax>464</ymax>
		</bndbox>
	</object>
	<object>
		<name>Downlight_LED_Einbauleuchten_Flur</name>
		<pose>Front</pose>
		<truncated>0</truncated>
		<bndbox>
			<xmin>93</xmin>
			<ymin>137</ymin>
			<xmax>200</xmax>
			<ymax>275</ymax>
		</bndbox>
	</object>
</annotation>