<annotation>
	<folder>training</folder>
	<filename>8496.jpg</filename>
	<path>/home/sdac_seminar/sdac_seminar_sose22/dataset/training/images/8496.jpg</path>
	<source>
		<database>Source</database>
	</source>
	<segmented>0</segmented>
	<size>
		<width>1024</width>
		<height>1024</height>
		<depth>3</depth>
	</size>
	<object>
		<name>WLAN</name>
		<pose>Front</pose>
		<truncated>0</truncated>
		<bndbox>
			<xmin>288</xmin>
			<ymin>616</ymin>
			<xmax>362</xmax>
			<ymax>690</ymax>
		</bndbox>
	</object>
	<object>
		<name>Downlight_LED_Einbauleuchten_Flur</name>
		<pose>Front</pose>
		<truncated>0</truncated>
		<bndbox>
			<xmin>787</xmin>
			<ymin>758</ymin>
			<xmax>833</xmax>
			<ymax>822</ymax>
		</bndbox>
	</object>
	<object>
		<name>Zugtaster</name>
		<pose>Front</pose>
		<truncated>0</truncated>
		<bndbox>
			<xmin>504</xmin>
			<ymin>634</ymin>
			<xmax>768</xmax>
			<ymax>916</ymax>
		</bndbox>
	</object>
	<object>
		<name>Zugtaster</name>
		<pose>Front</pose>
		<truncated>0</truncated>
		<bndbox>
			<xmin>108</xmin>
			<ymin>320</ymin>
			<xmax>180</xmax>
			<ymax>442</ymax>
		</bndbox>
	</object>
</annotation>