<annotation>
	<folder>training</folder>
	<filename>9129.jpg</filename>
	<path>/home/sdac_seminar/sdac_seminar_sose22/dataset/training/images/9129.jpg</path>
	<source>
		<database>Source</database>
	</source>
	<segmented>0</segmented>
	<size>
		<width>1024</width>
		<height>1024</height>
		<depth>3</depth>
	</size>
	<object>
		<name>Ausschalter_beleuchtet</name>
		<pose>Front</pose>
		<truncated>0</truncated>
		<bndbox>
			<xmin>77</xmin>
			<ymin>593</ymin>
			<xmax>189</xmax>
			<ymax>689</ymax>
		</bndbox>
	</object>
	<object>
		<name>Schukosteckdose_einfach</name>
		<pose>Front</pose>
		<truncated>0</truncated>
		<bndbox>
			<xmin>345</xmin>
			<ymin>509</ymin>
			<xmax>388</xmax>
			<ymax>559</ymax>
		</bndbox>
	</object>
	<object>
		<name>NAM-Nichtautomatischer_Melder</name>
		<pose>Front</pose>
		<truncated>0</truncated>
		<bndbox>
			<xmin>301</xmin>
			<ymin>122</ymin>
			<xmax>433</xmax>
			<ymax>254</ymax>
		</bndbox>
	</object>
	<object>
		<name>Ausschalter_beleuchtet</name>
		<pose>Front</pose>
		<truncated>0</truncated>
		<bndbox>
			<xmin>121</xmin>
			<ymin>808</ymin>
			<xmax>217</xmax>
			<ymax>920</ymax>
		</bndbox>
	</object>
	<object>
		<name>Schukosteckdose_einfach</name>
		<pose>Front</pose>
		<truncated>0</truncated>
		<bndbox>
			<xmin>872</xmin>
			<ymin>743</ymin>
			<xmax>972</xmax>
			<ymax>830</ymax>
		</bndbox>
	</object>
</annotation>