<annotation>
	<folder>training</folder>
	<filename>9365.jpg</filename>
	<path>/home/sdac_seminar/sdac_seminar_sose22/dataset/training/images/9365.jpg</path>
	<source>
		<database>Source</database>
	</source>
	<segmented>0</segmented>
	<size>
		<width>1024</width>
		<height>1024</height>
		<depth>3</depth>
	</size>
	<object>
		<name>ZD_Melder_in_Zwischendecke_mit_Revisionsoeffnung_mind_40_x_40_cm</name>
		<pose>Front</pose>
		<truncated>0</truncated>
		<bndbox>
			<xmin>651</xmin>
			<ymin>247</ymin>
			<xmax>765</xmax>
			<ymax>396</ymax>
		</bndbox>
	</object>
	<object>
		<name>Serienschalter</name>
		<pose>Front</pose>
		<truncated>0</truncated>
		<bndbox>
			<xmin>248</xmin>
			<ymin>437</ymin>
			<xmax>346</xmax>
			<ymax>523</ymax>
		</bndbox>
	</object>
	<object>
		<name>Ambulanz_Pendelleuchte_LED</name>
		<pose>Front</pose>
		<truncated>0</truncated>
		<bndbox>
			<xmin>533</xmin>
			<ymin>608</ymin>
			<xmax>589</xmax>
			<ymax>995</ymax>
		</bndbox>
	</object>
	<object>
		<name>Serienschalter</name>
		<pose>Front</pose>
		<truncated>0</truncated>
		<bndbox>
			<xmin>177</xmin>
			<ymin>543</ymin>
			<xmax>225</xmax>
			<ymax>627</ymax>
		</bndbox>
	</object>
	<object>
		<name>Ambulanz_Pendelleuchte_LED</name>
		<pose>Front</pose>
		<truncated>0</truncated>
		<bndbox>
			<xmin>103</xmin>
			<ymin>816</ymin>
			<xmax>877</xmax>
			<ymax>928</ymax>
		</bndbox>
	</object>
</annotation>