<annotation>
	<folder>training</folder>
	<filename>9368.jpg</filename>
	<path>/home/sdac_seminar/sdac_seminar_sose22/dataset/training/images/9368.jpg</path>
	<source>
		<database>Source</database>
	</source>
	<segmented>0</segmented>
	<size>
		<width>1024</width>
		<height>1024</height>
		<depth>3</depth>
	</size>
	<object>
		<name>WLAN</name>
		<pose>Front</pose>
		<truncated>0</truncated>
		<bndbox>
			<xmin>107</xmin>
			<ymin>186</ymin>
			<xmax>179</xmax>
			<ymax>258</ymax>
		</bndbox>
	</object>
	<object>
		<name>ASR_Ansaugoeffnung</name>
		<pose>Front</pose>
		<truncated>0</truncated>
		<bndbox>
			<xmin>159</xmin>
			<ymin>341</ymin>
			<xmax>247</xmax>
			<ymax>364</ymax>
		</bndbox>
	</object>
	<object>
		<name>Wechselschalter</name>
		<pose>Front</pose>
		<truncated>0</truncated>
		<bndbox>
			<xmin>232</xmin>
			<ymin>576</ymin>
			<xmax>328</xmax>
			<ymax>674</ymax>
		</bndbox>
	</object>
	<object>
		<name>Einbaudownlights_LED_Konferenzraeume</name>
		<pose>Front</pose>
		<truncated>0</truncated>
		<bndbox>
			<xmin>520</xmin>
			<ymin>521</ymin>
			<xmax>624</xmax>
			<ymax>671</ymax>
		</bndbox>
	</object>
	<object>
		<name>OT_Multisensormelder_(Kombination_RMO_WMD)</name>
		<pose>Front</pose>
		<truncated>0</truncated>
		<bndbox>
			<xmin>318</xmin>
			<ymin>450</ymin>
			<xmax>374</xmax>
			<ymax>506</ymax>
		</bndbox>
	</object>
	<object>
		<name>WLAN</name>
		<pose>Front</pose>
		<truncated>0</truncated>
		<bndbox>
			<xmin>590</xmin>
			<ymin>355</ymin>
			<xmax>642</xmax>
			<ymax>407</ymax>
		</bndbox>
	</object>
	<object>
		<name>ASR_Ansaugoeffnung</name>
		<pose>Front</pose>
		<truncated>0</truncated>
		<bndbox>
			<xmin>434</xmin>
			<ymin>108</ymin>
			<xmax>516</xmax>
			<ymax>185</ymax>
		</bndbox>
	</object>
	<object>
		<name>Wechselschalter</name>
		<pose>Front</pose>
		<truncated>0</truncated>
		<bndbox>
			<xmin>344</xmin>
			<ymin>168</ymin>
			<xmax>501</xmax>
			<ymax>312</ymax>
		</bndbox>
	</object>
	<object>
		<name>WLAN</name>
		<pose>Front</pose>
		<truncated>0</truncated>
		<bndbox>
			<xmin>237</xmin>
			<ymin>579</ymin>
			<xmax>305</xmax>
			<ymax>647</ymax>
		</bndbox>
	</object>
</annotation>