<annotation>
	<folder>training</folder>
	<filename>9426.jpg</filename>
	<path>/home/sdac_seminar/sdac_seminar_sose22/dataset/training/images/9426.jpg</path>
	<source>
		<database>Source</database>
	</source>
	<segmented>0</segmented>
	<size>
		<width>1024</width>
		<height>1024</height>
		<depth>3</depth>
	</size>
	<object>
		<name>WLAN</name>
		<pose>Front</pose>
		<truncated>0</truncated>
		<bndbox>
			<xmin>128</xmin>
			<ymin>806</ymin>
			<xmax>180</xmax>
			<ymax>858</ymax>
		</bndbox>
	</object>
	<object>
		<name>RMO_Rauchmelder_optischer</name>
		<pose>Front</pose>
		<truncated>0</truncated>
		<bndbox>
			<xmin>640</xmin>
			<ymin>827</ymin>
			<xmax>753</xmax>
			<ymax>940</ymax>
		</bndbox>
	</object>
	<object>
		<name>Gegensprechanlage_mit_Video</name>
		<pose>Front</pose>
		<truncated>0</truncated>
		<bndbox>
			<xmin>889</xmin>
			<ymin>426</ymin>
			<xmax>977</xmax>
			<ymax>473</ymax>
		</bndbox>
	</object>
	<object>
		<name>Ausschalter_beleuchtet</name>
		<pose>Front</pose>
		<truncated>0</truncated>
		<bndbox>
			<xmin>382</xmin>
			<ymin>409</ymin>
			<xmax>438</xmax>
			<ymax>457</ymax>
		</bndbox>
	</object>
	<object>
		<name>RMO_Rauchmelder_optischer</name>
		<pose>Front</pose>
		<truncated>0</truncated>
		<bndbox>
			<xmin>142</xmin>
			<ymin>215</ymin>
			<xmax>303</xmax>
			<ymax>376</ymax>
		</bndbox>
	</object>
	<object>
		<name>Ausschalter_beleuchtet</name>
		<pose>Front</pose>
		<truncated>0</truncated>
		<bndbox>
			<xmin>732</xmin>
			<ymin>475</ymin>
			<xmax>828</xmax>
			<ymax>587</ymax>
		</bndbox>
	</object>
	<object>
		<name>Ausschalter_beleuchtet</name>
		<pose>Front</pose>
		<truncated>0</truncated>
		<bndbox>
			<xmin>641</xmin>
			<ymin>830</ymin>
			<xmax>759</xmax>
			<ymax>932</ymax>
		</bndbox>
	</object>
</annotation>