<annotation>
	<folder>training</folder>
	<filename>9604.jpg</filename>
	<path>/home/sdac_seminar/sdac_seminar_sose22/dataset/training/images/9604.jpg</path>
	<source>
		<database>Source</database>
	</source>
	<segmented>0</segmented>
	<size>
		<width>1024</width>
		<height>1024</height>
		<depth>3</depth>
	</size>
	<object>
		<name>NAM-Nichtautomatischer_Melder</name>
		<pose>Front</pose>
		<truncated>0</truncated>
		<bndbox>
			<xmin>465</xmin>
			<ymin>128</ymin>
			<xmax>578</xmax>
			<ymax>241</ymax>
		</bndbox>
	</object>
	<object>
		<name>ASR_Ansaugoeffnung</name>
		<pose>Front</pose>
		<truncated>0</truncated>
		<bndbox>
			<xmin>764</xmin>
			<ymin>932</ymin>
			<xmax>828</xmax>
			<ymax>1021</ymax>
		</bndbox>
	</object>
	<object>
		<name>Downlight_LED_Einbauleuchten_Flur</name>
		<pose>Front</pose>
		<truncated>0</truncated>
		<bndbox>
			<xmin>115</xmin>
			<ymin>640</ymin>
			<xmax>256</xmax>
			<ymax>796</ymax>
		</bndbox>
	</object>
	<object>
		<name>NAM-Nichtautomatischer_Melder</name>
		<pose>Front</pose>
		<truncated>0</truncated>
		<bndbox>
			<xmin>455</xmin>
			<ymin>509</ymin>
			<xmax>608</xmax>
			<ymax>662</ymax>
		</bndbox>
	</object>
	<object>
		<name>ASR_Ansaugoeffnung</name>
		<pose>Front</pose>
		<truncated>0</truncated>
		<bndbox>
			<xmin>342</xmin>
			<ymin>917</ymin>
			<xmax>518</xmax>
			<ymax>963</ymax>
		</bndbox>
	</object>
	<object>
		<name>OKW_Multisensormelder_(Kombination_optischer_Rauch-Kahlenmonoxid_Waerme-Melder)</name>
		<pose>Front</pose>
		<truncated>0</truncated>
		<bndbox>
			<xmin>271</xmin>
			<ymin>408</ymin>
			<xmax>403</xmax>
			<ymax>540</ymax>
		</bndbox>
	</object>
	<object>
		<name>Downlight_LED_Einbauleuchten_Flur</name>
		<pose>Front</pose>
		<truncated>0</truncated>
		<bndbox>
			<xmin>85</xmin>
			<ymin>882</ymin>
			<xmax>218</xmax>
			<ymax>980</ymax>
		</bndbox>
	</object>
	<object>
		<name>ASR_Ansaugoeffnung</name>
		<pose>Front</pose>
		<truncated>0</truncated>
		<bndbox>
			<xmin>357</xmin>
			<ymin>919</ymin>
			<xmax>380</xmax>
			<ymax>1007</ymax>
		</bndbox>
	</object>
</annotation>