<annotation>
	<folder>training</folder>
	<filename>9810.jpg</filename>
	<path>/home/sdac_seminar/sdac_seminar_sose22/dataset/training/images/9810.jpg</path>
	<source>
		<database>Source</database>
	</source>
	<segmented>0</segmented>
	<size>
		<width>1024</width>
		<height>1024</height>
		<depth>3</depth>
	</size>
	<object>
		<name>ROA_Rauchmelder_optisch_mit_Signalgeber_(Sockelsirene)</name>
		<pose>Front</pose>
		<truncated>0</truncated>
		<bndbox>
			<xmin>167</xmin>
			<ymin>361</ymin>
			<xmax>223</xmax>
			<ymax>417</ymax>
		</bndbox>
	</object>
	<object>
		<name>NAM-Nichtautomatischer_Melder</name>
		<pose>Front</pose>
		<truncated>0</truncated>
		<bndbox>
			<xmin>579</xmin>
			<ymin>192</ymin>
			<xmax>710</xmax>
			<ymax>323</ymax>
		</bndbox>
	</object>
	<object>
		<name>ZD_Melder_in_Zwischendecke_mit_Revisionsoeffnung_mind_40_x_40_cm</name>
		<pose>Front</pose>
		<truncated>0</truncated>
		<bndbox>
			<xmin>382</xmin>
			<ymin>892</ymin>
			<xmax>456</xmax>
			<ymax>949</ymax>
		</bndbox>
	</object>
	<object>
		<name>NAM-Nichtautomatischer_Melder</name>
		<pose>Front</pose>
		<truncated>0</truncated>
		<bndbox>
			<xmin>246</xmin>
			<ymin>792</ymin>
			<xmax>359</xmax>
			<ymax>905</ymax>
		</bndbox>
	</object>
</annotation>